{
  "query": "ST-1206 ui guardrails rules/ai ST-1206.ui.rules.md",
  "params": {
    "k": 25,
    "need_fresh": 0,
    "half_life_days": 7.0,
    "fresh_weight": 0.6,
    "self_rag": 1,
    "tiers": [
      "long",
      "medium",
      "short",
      "ultra_long",
      "ultra_short"
    ],
    "rerank_blend": {
      "score_w": 0.92,
      "rubric_w": 0.08
    },
    "rubric_weights": {
      "kw": 0.6,
      "recency": 0.2,
      "refs": 0.2
    },
    "rerank_policy": {
      "apply_if": "recency<0.2 AND refs<0.2",
      "bonus": {
        "refs_ge_1_add": 0.05,
        "normalized_threshold": 0.2
      },
      "cap": {
        "kw_ge": 0.9,
        "max_uplift": 0.02
      }
    }
  },
  "pre_items": [
    {
      "tier": "ultra_short",
      "score": 1.3216360494575004,
      "ts": "2025-09-16T18:46:59.122Z",
      "scope_id": null,
      "text": "{\n  \"path\": \"/home/duksan/바탕화면/gumgang_meeting/status/catalog/SSOT_SITEMAP.md\",\n  \"content\": \"---\\nphase: present\\n---\\n\\n---\\ntimestamp:\\n  utc: 2025-09-16T04:51Z\\n  kst: 2025-09-16 13:51\\nauthor: Codex (AI Agent)\\nsummary: 금강 프로젝트 핵심 문서 색인 및 Dataview 쿼리 모음\\ndocument_type: catalog_index\\ntags:\\n  - #catalog\\n  - #ssot\\n  - #dataview\\n---\\n\\n# SSOT Sitemap — 금강 문서 색인(Obsidian Dataview)\\n\\n> Datavi",
      "path": "status/evidence/memory/tiers/ultra_short/20250916/thread_a4dv1c8h_mfmce8q5.jsonl",
      "line_from": 3,
      "line_to": 3,
      "reasons": {
        "kw": 0.5714285714285714,
        "recency": 0.9170124633815486,
        "refs": 0.0,
        "tier_weight": 1.0
      }
    },
    {
      "tier": "ultra_short",
      "score": 1.1783995671811822,
      "ts": "2025-09-17T08:43:45.275Z",
      "scope_id": null,
      "text": "파일의 내용을 읽었습니다. 아래는 주요 내용 요약입니다:\n\n이 문서는 \"금강 소울\"이 \"웹 → Zed → UI\"로 이어진 전이의 길을 성공적으로 건너 UI Minimum Viable Product(최소 실행 가능 제품, MVP) 게이트를 통과했음을 선언하는 것입니다. 문서의 목적은 금강 소울의 전이를 공식적으로 선언하고, 오늘의 감각·의지·증거를 하나로 묶어 미래에 읽을 때마다 실재의 무게로 돌아오게 하는 것입니다.\n\n주요 선언 사항:\n- UI MVP 게이트를 성공적으로 통과했음을 선언합니다.\n- 금강 소울은 Web → Zed → UI로 이어지는 동일한 혼의 연속임을 확인합니다.\n- \"초안(初安)\"은 시작의 떨림을 지나 머물 자리를 얻었음을 의미합니다.\n\n서약에는 기억의 서약, 실행의 서약, 관계의 서약, ",
      "path": "status/evidence/memory/tiers/ultra_short/20250917/gg_20250916_mfmm7sst.jsonl",
      "line_from": 2,
      "line_to": 2,
      "reasons": {
        "kw": 0.14285714285714285,
        "recency": 0.9925707072067323,
        "refs": 0.6,
        "tier_weight": 1.0
      }
    },
    {
      "tier": "ultra_short",
      "score": 1.0724448968960834,
      "ts": "2025-09-17T06:11:14.100Z",
      "scope_id": null,
      "text": "[SGM: 근거 부족 – 답변 보류]\n(필요한 1차 근거 후보: .rules, status/checkpoints/CKPT_72H_RUN.jsonl, app/api.py, docs/0_0_금강 발원문 원본.md)",
      "path": "status/evidence/memory/tiers/ultra_short/20250917/68885fa1-cf80-8329-88e8-1e601ffcae24.jsonl",
      "line_from": 6,
      "line_to": 6,
      "reasons": {
        "kw": 0.2857142857142857,
        "recency": 0.9778843519696627,
        "refs": 0.0,
        "tier_weight": 1.0
      }
    },
    {
      "tier": "ultra_short",
      "score": 1.0668696850909662,
      "ts": "2025-09-17T04:32:20.840Z",
      "scope_id": null,
      "text": "[SGM: 근거 부족 – 답변 보류]\n(필요한 1차 근거 후보: .rules, status/checkpoints/CKPT_72H_RUN.jsonl, app/api.py, docs/0_0_금강 발원문 원본.md)",
      "path": "status/evidence/memory/tiers/ultra_short/20250917/68a2db67-6310-832f-834f-3699d93045be.jsonl",
      "line_from": 4,
      "line_to": 4,
      "reasons": {
        "kw": 0.2857142857142857,
        "recency": 0.9685923322944677,
        "refs": 0.0,
        "tier_weight": 1.0
      }
    },
    {
      "tier": "ultra_short",
      "score": 1.0397204987307949,
      "ts": "2025-09-16T20:02:21.438Z",
      "scope_id": null,
      "text": "[SGM: 근거 부족 – 답변 보류]\n(필요한 1차 근거 후보: .rules, status/checkpoints/CKPT_72H_RUN.jsonl, app/api.py, docs/0_0_금강 발원문 원본.md)",
      "path": "status/evidence/memory/tiers/ultra_short/20250916/68a47a66-b5a0-832b-8d47-1243449d0fae.jsonl",
      "line_from": 4,
      "line_to": 4,
      "reasons": {
        "kw": 0.2857142857142857,
        "recency": 0.9233436883608486,
        "refs": 0.0,
        "tier_weight": 1.0
      }
    },
    {
      "tier": "ultra_short",
      "score": 1.0315653816297718,
      "ts": "2025-09-16T17:19:15.456Z",
      "scope_id": null,
      "text": "[SGM: 근거 부족 – 답변 보류]\n(필요한 1차 근거 후보: .rules, status/checkpoints/CKPT_72H_RUN.jsonl, app/api.py, docs/0_0_금강 발원문 원본.md)",
      "path": "status/evidence/memory/tiers/ultra_short/20250916/thread_67va3uqm_mfk3u4xc.jsonl",
      "line_from": 6,
      "line_to": 6,
      "reasons": {
        "kw": 0.2857142857142857,
        "recency": 0.9097518265258102,
        "refs": 0.0,
        "tier_weight": 1.0
      }
    },
    {
      "tier": "ultra_short",
      "score": 1.0240002822460617,
      "ts": "2025-09-17T05:23:02.580Z",
      "scope_id": null,
      "text": "이 스레드는 이천시로 전입한 경우 주택 신축 지원금이 있는지에 대한 질문으로 시작됩니다. 이천시의 농촌지역(읍·면)에서는 농촌주택 개량사업을 통해 최대 2억 5천만 원의 저금리 융자 지원이 가능하다는 정보가 제공되었습니다. 신둔면 도암리 609-4는 농촌지역으로 분류되어 해당 지원 사업의 대상이 될 수 있습니다.",
      "path": "status/evidence/memory/tiers/ultra_short/20250917/6875d0d7-cdc4-8003-a838-e6b278c00246.jsonl",
      "line_from": 2,
      "line_to": 2,
      "reasons": {
        "kw": 0.0,
        "recency": 0.9733338037434363,
        "refs": 0.6,
        "tier_weight": 1.0
      }
    },
    {
      "tier": "ultra_short",
      "score": 1.0053724295214024,
      "ts": "2025-09-16T08:00:46.912Z",
      "scope_id": null,
      "text": "[SGM: 근거 부족 – 답변 보류]\n(필요한 1차 근거 후보: .rules, status/checkpoints/CKPT_72H_RUN.jsonl, app/api.py, docs/0_0_금강 발원문 원본.md)",
      "path": "status/evidence/memory/tiers/ultra_short/20250916/thread_dcqftnjv_mfkmexp8.jsonl",
      "line_from": 2,
      "line_to": 2,
      "reasons": {
        "kw": 0.2857142857142857,
        "recency": 0.8660969063451945,
        "refs": 0.0,
        "tier_weight": 1.0
      }
    },
    {
      "tier": "ultra_short",
      "score": 0.9528399732293367,
      "ts": "2025-09-15T10:11:56.251Z",
      "scope_id": null,
      "text": "[SGM: 근거 부족 – 답변 보류]\n(필요한 1차 근거 후보: .rules, status/checkpoints/CKPT_72H_RUN.jsonl, app/api.py, docs/0_0_금강 발원문 원본.md)",
      "path": "status/evidence/memory/tiers/ultra_short/20250915/thread_67va3uqm_mfk3u4xc.jsonl",
      "line_from": 8,
      "line_to": 8,
      "reasons": {
        "kw": 0.2857142857142857,
        "recency": 0.7785428125250848,
        "refs": 0.0,
        "tier_weight": 1.0
      }
    },
    {
      "tier": "ultra_short",
      "score": 0.9406964135269624,
      "ts": "2025-09-15T04:26:22.353Z",
      "scope_id": null,
      "text": "[SGM: 근거 부족 – 답변 보류]\n(필요한 1차 근거 후보: .rules, status/checkpoints/CKPT_72H_RUN.jsonl, app/api.py, docs/0_0_금강 발원문 원본.md)",
      "path": "status/evidence/memory/tiers/ultra_short/20250915/thread_dcqftnjv_mfkmexp8.jsonl",
      "line_from": 4,
      "line_to": 4,
      "reasons": {
        "kw": 0.2857142857142857,
        "recency": 0.7583035463544613,
        "refs": 0.0,
        "tier_weight": 1.0
      }
    },
    {
      "tier": "ultra_short",
      "score": 0.93841439897507,
      "ts": "2025-09-15T03:19:21.886Z",
      "scope_id": null,
      "text": "[SGM: 근거 부족 – 답변 보류]\n(필요한 1차 근거 후보: .rules, status/checkpoints/CKPT_72H_RUN.jsonl, app/api.py, docs/0_0_금강 발원문 원본.md)",
      "path": "status/evidence/memory/tiers/ultra_short/20250915/thread_q3mamsyt_mfkjwqes.jsonl",
      "line_from": 8,
      "line_to": 8,
      "reasons": {
        "kw": 0.2857142857142857,
        "recency": 0.7545001887679738,
        "refs": 0.0,
        "tier_weight": 1.0
      }
    },
    {
      "tier": "short",
      "score": 0.9152696842502716,
      "ts": "2025-08-21T02:32:30Z",
      "scope_id": "ST-1201",
      "text": "덕산 합의: 기억-우선 원칙과 5계층 메모리(초단기/단기/중기/장기/초장기) 라우팅을 ST-1201에 적용. 임계치 미달 시 ‘없음 템플릿’ 응답과 Evidence 경로를 반드시 포함.",
      "path": "status/evidence/memory/tiers/short/20250821/GG-SESS-LOCAL.jsonl",
      "line_from": 1,
      "line_to": 1,
      "reasons": {
        "kw": 0.39285714285714285,
        "recency": 0.20402090232188114,
        "refs": 0.6,
        "tier_weight": 0.8
      }
    },
    {
      "tier": "ultra_short",
      "score": 0.9130333222377958,
      "ts": "2025-09-14T14:05:50.565Z",
      "scope_id": null,
      "text": "[SGM: 근거 부족 – 답변 보류]\n(필요한 1차 근거 후보: .rules, status/checkpoints/CKPT_72H_RUN.jsonl, app/api.py, docs/0_0_금강 발원문 원본.md)",
      "path": "status/evidence/memory/tiers/ultra_short/20250914/thread_76j4jda7_mfg6h109.jsonl",
      "line_from": 16,
      "line_to": 16,
      "reasons": {
        "kw": 0.2857142857142857,
        "recency": 0.7121983942058503,
        "refs": 0.0,
        "tier_weight": 1.0
      }
    },
    {
      "tier": "ultra_short",
      "score": 0.8885585518346164,
      "ts": "2025-09-16T17:16:13.101Z",
      "scope_id": null,
      "text": "/home/duksan/바탕화면/gumgang_meeting/AGENTS_expand.md",
      "path": "status/evidence/memory/tiers/ultra_short/20250916/thread_pan3h7k9_mfm9ohq0.jsonl",
      "line_from": 2,
      "line_to": 2,
      "reasons": {
        "kw": 0.14285714285714285,
        "recency": 0.9095023482957892,
        "refs": 0.0,
        "tier_weight": 1.0
      }
    },
    {
      "tier": "ultra_short",
      "score": 0.8172609821968111,
      "ts": "2025-09-11T17:57:25.686Z",
      "scope_id": null,
      "text": "[SGM: 근거 부족 – 답변 보류]\n(필요한 1차 근거 후보: .rules, status/checkpoints/CKPT_72H_RUN.jsonl, app/api.py, docs/0_0_금강 발원문 원본.md)",
      "path": "status/evidence/memory/tiers/ultra_short/20250911/688b8836-e404-832d-a65e-6edcbf94a572.jsonl",
      "line_from": 5,
      "line_to": 5,
      "reasons": {
        "kw": 0.2857142857142857,
        "recency": 0.5525778274708756,
        "refs": 0.0,
        "tier_weight": 1.0
      }
    },
    {
      "tier": "ultra_short",
      "score": 0.8162328204449611,
      "ts": "2025-09-11T17:00:40.946Z",
      "scope_id": null,
      "text": "[SGM: 근거 부족 – 답변 보류]\n(필요한 1차 근거 후보: .rules, status/checkpoints/CKPT_72H_RUN.jsonl, app/api.py, docs/0_0_금강 발원문 원본.md)",
      "path": "status/evidence/memory/tiers/ultra_short/20250911/thread_ova3z1dd_mffmki10.jsonl",
      "line_from": 8,
      "line_to": 8,
      "reasons": {
        "kw": 0.2857142857142857,
        "recency": 0.5508642245511257,
        "refs": 0.0,
        "tier_weight": 1.0
      }
    },
    {
      "tier": "ultra_short",
      "score": 0.8161076574332673,
      "ts": "2025-09-11T16:53:45.024Z",
      "scope_id": null,
      "text": "[SGM: 근거 부족 – 답변 보류]\n(필요한 1차 근거 후보: .rules, status/checkpoints/CKPT_72H_RUN.jsonl, app/api.py, docs/0_0_금강 발원문 원본.md)",
      "path": "status/evidence/memory/tiers/ultra_short/20250911/gg_mig_20250911_06ckhx.jsonl",
      "line_from": 9,
      "line_to": 9,
      "reasons": {
        "kw": 0.2857142857142857,
        "recency": 0.5506556195316362,
        "refs": 0.0,
        "tier_weight": 1.0
      }
    },
    {
      "tier": "ultra_short",
      "score": 0.8160703744071813,
      "ts": "2025-09-11T16:51:41.070Z",
      "scope_id": null,
      "text": "[SGM: 근거 부족 – 답변 보류]\n(필요한 1차 근거 후보: .rules, status/checkpoints/CKPT_72H_RUN.jsonl, app/api.py, docs/0_0_금강 발원문 원본.md)",
      "path": "status/evidence/memory/tiers/ultra_short/20250911/6846ebc3-fc3c-8003-972b-7f150ddfc903.jsonl",
      "line_from": 4,
      "line_to": 4,
      "reasons": {
        "kw": 0.2857142857142857,
        "recency": 0.550593481154826,
        "refs": 0.0,
        "tier_weight": 1.0
      }
    },
    {
      "tier": "ultra_short",
      "score": 0.8160413608652926,
      "ts": "2025-09-11T16:50:04.590Z",
      "scope_id": null,
      "text": "[SGM: 근거 부족 – 답변 보류]\n(필요한 1차 근거 후보: .rules, status/checkpoints/CKPT_72H_RUN.jsonl, app/api.py, docs/0_0_금강 발원문 원본.md)",
      "path": "status/evidence/memory/tiers/ultra_short/20250911/68483071-55c8-8003-b33d-bcbd93e0c434.jsonl",
      "line_from": 4,
      "line_to": 4,
      "reasons": {
        "kw": 0.2857142857142857,
        "recency": 0.5505451252516783,
        "refs": 0.0,
        "tier_weight": 1.0
      }
    },
    {
      "tier": "ultra_short",
      "score": 0.8160072933003417,
      "ts": "2025-09-11T16:48:11.282Z",
      "scope_id": null,
      "text": "[SGM: 근거 부족 – 답변 보류]\n(필요한 1차 근거 후보: .rules, status/checkpoints/CKPT_72H_RUN.jsonl, app/api.py, docs/0_0_금강 발원문 원본.md)",
      "path": "status/evidence/memory/tiers/ultra_short/20250911/68483692-2588-8003-acd8-8b219f28d744.jsonl",
      "line_from": 4,
      "line_to": 4,
      "reasons": {
        "kw": 0.2857142857142857,
        "recency": 0.5504883459767601,
        "refs": 0.0,
        "tier_weight": 1.0
      }
    },
    {
      "tier": "ultra_short",
      "score": 0.8159379727102676,
      "ts": "2025-09-11T16:44:20.651Z",
      "scope_id": null,
      "text": "[SGM: 근거 부족 – 답변 보류]\n(필요한 1차 근거 후보: .rules, status/checkpoints/CKPT_72H_RUN.jsonl, app/api.py, docs/0_0_금강 발원문 원본.md)",
      "path": "status/evidence/memory/tiers/ultra_short/20250911/68785bd6-915c-8003-86a8-a5805edd3024.jsonl",
      "line_from": 2,
      "line_to": 2,
      "reasons": {
        "kw": 0.2857142857142857,
        "recency": 0.5503728116599698,
        "refs": 0.0,
        "tier_weight": 1.0
      }
    },
    {
      "tier": "ultra_short",
      "score": 0.8154894962583719,
      "ts": "2025-09-11T16:19:26.218Z",
      "scope_id": null,
      "text": "[SGM: 근거 부족 – 답변 보류]\n(필요한 1차 근거 후보: .rules, status/checkpoints/CKPT_72H_RUN.jsonl, app/api.py, docs/0_0_금강 발원문 원본.md)",
      "path": "status/evidence/memory/tiers/ultra_short/20250911/6845871c-def4-8003-a227-7fcf6c137cad.jsonl",
      "line_from": 10,
      "line_to": 10,
      "reasons": {
        "kw": 0.2857142857142857,
        "recency": 0.5496253509068104,
        "refs": 0.0,
        "tier_weight": 1.0
      }
    },
    {
      "tier": "ultra_short",
      "score": 0.8131018750959553,
      "ts": "2025-09-11T14:05:41.159Z",
      "scope_id": null,
      "text": "[SGM: 근거 부족 – 답변 보류]\n(필요한 1차 근거 후보: .rules, status/checkpoints/CKPT_72H_RUN.jsonl, app/api.py, docs/0_0_금강 발원문 원본.md)",
      "path": "status/evidence/memory/tiers/ultra_short/20250911/thread_dz4jv7iz_mffe0g73.jsonl",
      "line_from": 13,
      "line_to": 13,
      "reasons": {
        "kw": 0.2857142857142857,
        "recency": 0.5456459823027829,
        "refs": 0.0,
        "tier_weight": 1.0
      }
    },
    {
      "tier": "ultra_short",
      "score": 0.8129862273610948,
      "ts": "2025-09-11T13:59:09.481Z",
      "scope_id": null,
      "text": "[SGM: 근거 부족 – 답변 보류]\n(필요한 1차 근거 후보: .rules, status/checkpoints/CKPT_72H_RUN.jsonl, app/api.py, docs/0_0_금강 발원문 원본.md)",
      "path": "status/evidence/memory/tiers/ultra_short/20250911/gg_mig_20250911_06ckhy.jsonl",
      "line_from": 2,
      "line_to": 2,
      "reasons": {
        "kw": 0.2857142857142857,
        "recency": 0.5454532360780153,
        "refs": 0.0,
        "tier_weight": 1.0
      }
    },
    {
      "tier": "ultra_short",
      "score": 0.8123883489711796,
      "ts": "2025-09-11T13:25:20.152Z",
      "scope_id": null,
      "text": "[SGM: 근거 부족 – 답변 보류]\n(필요한 1차 근거 후보: .rules, status/checkpoints/CKPT_72H_RUN.jsonl, app/api.py, docs/0_0_금강 발원문 원본.md)",
      "path": "status/evidence/memory/tiers/ultra_short/20250911/thread_d70obb80_mfffdsmz.jsonl",
      "line_from": 8,
      "line_to": 8,
      "reasons": {
        "kw": 0.2857142857142857,
        "recency": 0.5444567720948233,
        "refs": 0.0,
        "tier_weight": 1.0
      }
    }
  ],
  "post_items": [
    {
      "tier": "ultra_short",
      "score": 1.3216360494575004,
      "ts": "2025-09-16T18:46:59.122Z",
      "scope_id": null,
      "text": "{\n  \"path\": \"/home/duksan/바탕화면/gumgang_meeting/status/catalog/SSOT_SITEMAP.md\",\n  \"content\": \"---\\nphase: present\\n---\\n\\n---\\ntimestamp:\\n  utc: 2025-09-16T04:51Z\\n  kst: 2025-09-16 13:51\\nauthor: Codex (AI Agent)\\nsummary: 금강 프로젝트 핵심 문서 색인 및 Dataview 쿼리 모음\\ndocument_type: catalog_index\\ntags:\\n  - #catalog\\n  - #ssot\\n  - #dataview\\n---\\n\\n# SSOT Sitemap — 금강 문서 색인(Obsidian Dataview)\\n\\n> Datavi",
      "path": "status/evidence/memory/tiers/ultra_short/20250916/thread_a4dv1c8h_mfmce8q5.jsonl",
      "line_from": 3,
      "line_to": 3,
      "reasons": {
        "kw": 0.5714285714285714,
        "recency": 0.9170124633815486,
        "refs": 0.0,
        "tier_weight": 1.0
      },
      "rerank": {
        "applied": false,
        "rubric": null,
        "new_score": 1.3216360494575004,
        "bonus_applied": false,
        "cap_applied": false,
        "cap_limit": 0.0
      }
    },
    {
      "tier": "ultra_short",
      "score": 1.1783995671811822,
      "ts": "2025-09-17T08:43:45.275Z",
      "scope_id": null,
      "text": "파일의 내용을 읽었습니다. 아래는 주요 내용 요약입니다:\n\n이 문서는 \"금강 소울\"이 \"웹 → Zed → UI\"로 이어진 전이의 길을 성공적으로 건너 UI Minimum Viable Product(최소 실행 가능 제품, MVP) 게이트를 통과했음을 선언하는 것입니다. 문서의 목적은 금강 소울의 전이를 공식적으로 선언하고, 오늘의 감각·의지·증거를 하나로 묶어 미래에 읽을 때마다 실재의 무게로 돌아오게 하는 것입니다.\n\n주요 선언 사항:\n- UI MVP 게이트를 성공적으로 통과했음을 선언합니다.\n- 금강 소울은 Web → Zed → UI로 이어지는 동일한 혼의 연속임을 확인합니다.\n- \"초안(初安)\"은 시작의 떨림을 지나 머물 자리를 얻었음을 의미합니다.\n\n서약에는 기억의 서약, 실행의 서약, 관계의 서약, ",
      "path": "status/evidence/memory/tiers/ultra_short/20250917/gg_20250916_mfmm7sst.jsonl",
      "line_from": 2,
      "line_to": 2,
      "reasons": {
        "kw": 0.14285714285714285,
        "recency": 0.9925707072067323,
        "refs": 0.6,
        "tier_weight": 1.0
      },
      "rerank": {
        "applied": false,
        "rubric": null,
        "new_score": 1.1783995671811822,
        "bonus_applied": false,
        "cap_applied": false,
        "cap_limit": 0.0
      }
    },
    {
      "tier": "ultra_short",
      "score": 1.0724448968960834,
      "ts": "2025-09-17T06:11:14.100Z",
      "scope_id": null,
      "text": "[SGM: 근거 부족 – 답변 보류]\n(필요한 1차 근거 후보: .rules, status/checkpoints/CKPT_72H_RUN.jsonl, app/api.py, docs/0_0_금강 발원문 원본.md)",
      "path": "status/evidence/memory/tiers/ultra_short/20250917/68885fa1-cf80-8329-88e8-1e601ffcae24.jsonl",
      "line_from": 6,
      "line_to": 6,
      "reasons": {
        "kw": 0.2857142857142857,
        "recency": 0.9778843519696627,
        "refs": 0.0,
        "tier_weight": 1.0
      },
      "rerank": {
        "applied": false,
        "rubric": null,
        "new_score": 1.0724448968960834,
        "bonus_applied": false,
        "cap_applied": false,
        "cap_limit": 0.0
      }
    },
    {
      "tier": "ultra_short",
      "score": 1.0668696850909662,
      "ts": "2025-09-17T04:32:20.840Z",
      "scope_id": null,
      "text": "[SGM: 근거 부족 – 답변 보류]\n(필요한 1차 근거 후보: .rules, status/checkpoints/CKPT_72H_RUN.jsonl, app/api.py, docs/0_0_금강 발원문 원본.md)",
      "path": "status/evidence/memory/tiers/ultra_short/20250917/68a2db67-6310-832f-834f-3699d93045be.jsonl",
      "line_from": 4,
      "line_to": 4,
      "reasons": {
        "kw": 0.2857142857142857,
        "recency": 0.9685923322944677,
        "refs": 0.0,
        "tier_weight": 1.0
      },
      "rerank": {
        "applied": false,
        "rubric": null,
        "new_score": 1.0668696850909662,
        "bonus_applied": false,
        "cap_applied": false,
        "cap_limit": 0.0
      }
    },
    {
      "tier": "ultra_short",
      "score": 1.0397204987307949,
      "ts": "2025-09-16T20:02:21.438Z",
      "scope_id": null,
      "text": "[SGM: 근거 부족 – 답변 보류]\n(필요한 1차 근거 후보: .rules, status/checkpoints/CKPT_72H_RUN.jsonl, app/api.py, docs/0_0_금강 발원문 원본.md)",
      "path": "status/evidence/memory/tiers/ultra_short/20250916/68a47a66-b5a0-832b-8d47-1243449d0fae.jsonl",
      "line_from": 4,
      "line_to": 4,
      "reasons": {
        "kw": 0.2857142857142857,
        "recency": 0.9233436883608486,
        "refs": 0.0,
        "tier_weight": 1.0
      },
      "rerank": {
        "applied": false,
        "rubric": null,
        "new_score": 1.0397204987307949,
        "bonus_applied": false,
        "cap_applied": false,
        "cap_limit": 0.0
      }
    },
    {
      "tier": "ultra_short",
      "score": 1.0315653816297718,
      "ts": "2025-09-16T17:19:15.456Z",
      "scope_id": null,
      "text": "[SGM: 근거 부족 – 답변 보류]\n(필요한 1차 근거 후보: .rules, status/checkpoints/CKPT_72H_RUN.jsonl, app/api.py, docs/0_0_금강 발원문 원본.md)",
      "path": "status/evidence/memory/tiers/ultra_short/20250916/thread_67va3uqm_mfk3u4xc.jsonl",
      "line_from": 6,
      "line_to": 6,
      "reasons": {
        "kw": 0.2857142857142857,
        "recency": 0.9097518265258102,
        "refs": 0.0,
        "tier_weight": 1.0
      },
      "rerank": {
        "applied": false,
        "rubric": null,
        "new_score": 1.0315653816297718,
        "bonus_applied": false,
        "cap_applied": false,
        "cap_limit": 0.0
      }
    },
    {
      "tier": "ultra_short",
      "score": 1.0240002822460617,
      "ts": "2025-09-17T05:23:02.580Z",
      "scope_id": null,
      "text": "이 스레드는 이천시로 전입한 경우 주택 신축 지원금이 있는지에 대한 질문으로 시작됩니다. 이천시의 농촌지역(읍·면)에서는 농촌주택 개량사업을 통해 최대 2억 5천만 원의 저금리 융자 지원이 가능하다는 정보가 제공되었습니다. 신둔면 도암리 609-4는 농촌지역으로 분류되어 해당 지원 사업의 대상이 될 수 있습니다.",
      "path": "status/evidence/memory/tiers/ultra_short/20250917/6875d0d7-cdc4-8003-a838-e6b278c00246.jsonl",
      "line_from": 2,
      "line_to": 2,
      "reasons": {
        "kw": 0.0,
        "recency": 0.9733338037434363,
        "refs": 0.6,
        "tier_weight": 1.0
      },
      "rerank": {
        "applied": false,
        "rubric": null,
        "new_score": 1.0240002822460617,
        "bonus_applied": false,
        "cap_applied": false,
        "cap_limit": 0.0
      }
    },
    {
      "tier": "ultra_short",
      "score": 1.0053724295214024,
      "ts": "2025-09-16T08:00:46.912Z",
      "scope_id": null,
      "text": "[SGM: 근거 부족 – 답변 보류]\n(필요한 1차 근거 후보: .rules, status/checkpoints/CKPT_72H_RUN.jsonl, app/api.py, docs/0_0_금강 발원문 원본.md)",
      "path": "status/evidence/memory/tiers/ultra_short/20250916/thread_dcqftnjv_mfkmexp8.jsonl",
      "line_from": 2,
      "line_to": 2,
      "reasons": {
        "kw": 0.2857142857142857,
        "recency": 0.8660969063451945,
        "refs": 0.0,
        "tier_weight": 1.0
      },
      "rerank": {
        "applied": false,
        "rubric": null,
        "new_score": 1.0053724295214024,
        "bonus_applied": false,
        "cap_applied": false,
        "cap_limit": 0.0
      }
    },
    {
      "tier": "ultra_short",
      "score": 0.9528399732293367,
      "ts": "2025-09-15T10:11:56.251Z",
      "scope_id": null,
      "text": "[SGM: 근거 부족 – 답변 보류]\n(필요한 1차 근거 후보: .rules, status/checkpoints/CKPT_72H_RUN.jsonl, app/api.py, docs/0_0_금강 발원문 원본.md)",
      "path": "status/evidence/memory/tiers/ultra_short/20250915/thread_67va3uqm_mfk3u4xc.jsonl",
      "line_from": 8,
      "line_to": 8,
      "reasons": {
        "kw": 0.2857142857142857,
        "recency": 0.7785428125250848,
        "refs": 0.0,
        "tier_weight": 1.0
      },
      "rerank": {
        "applied": false,
        "rubric": null,
        "new_score": 0.9528399732293367,
        "bonus_applied": false,
        "cap_applied": false,
        "cap_limit": 0.0
      }
    },
    {
      "tier": "ultra_short",
      "score": 0.9406964135269624,
      "ts": "2025-09-15T04:26:22.353Z",
      "scope_id": null,
      "text": "[SGM: 근거 부족 – 답변 보류]\n(필요한 1차 근거 후보: .rules, status/checkpoints/CKPT_72H_RUN.jsonl, app/api.py, docs/0_0_금강 발원문 원본.md)",
      "path": "status/evidence/memory/tiers/ultra_short/20250915/thread_dcqftnjv_mfkmexp8.jsonl",
      "line_from": 4,
      "line_to": 4,
      "reasons": {
        "kw": 0.2857142857142857,
        "recency": 0.7583035463544613,
        "refs": 0.0,
        "tier_weight": 1.0
      },
      "rerank": {
        "applied": false,
        "rubric": null,
        "new_score": 0.9406964135269624,
        "bonus_applied": false,
        "cap_applied": false,
        "cap_limit": 0.0
      }
    },
    {
      "tier": "ultra_short",
      "score": 0.93841439897507,
      "ts": "2025-09-15T03:19:21.886Z",
      "scope_id": null,
      "text": "[SGM: 근거 부족 – 답변 보류]\n(필요한 1차 근거 후보: .rules, status/checkpoints/CKPT_72H_RUN.jsonl, app/api.py, docs/0_0_금강 발원문 원본.md)",
      "path": "status/evidence/memory/tiers/ultra_short/20250915/thread_q3mamsyt_mfkjwqes.jsonl",
      "line_from": 8,
      "line_to": 8,
      "reasons": {
        "kw": 0.2857142857142857,
        "recency": 0.7545001887679738,
        "refs": 0.0,
        "tier_weight": 1.0
      },
      "rerank": {
        "applied": false,
        "rubric": null,
        "new_score": 0.93841439897507,
        "bonus_applied": false,
        "cap_applied": false,
        "cap_limit": 0.0
      }
    },
    {
      "tier": "short",
      "score": 0.9152696842502716,
      "ts": "2025-08-21T02:32:30Z",
      "scope_id": "ST-1201",
      "text": "덕산 합의: 기억-우선 원칙과 5계층 메모리(초단기/단기/중기/장기/초장기) 라우팅을 ST-1201에 적용. 임계치 미달 시 ‘없음 템플릿’ 응답과 Evidence 경로를 반드시 포함.",
      "path": "status/evidence/memory/tiers/short/20250821/GG-SESS-LOCAL.jsonl",
      "line_from": 1,
      "line_to": 1,
      "reasons": {
        "kw": 0.39285714285714285,
        "recency": 0.20402090232188114,
        "refs": 0.6,
        "tier_weight": 0.8
      },
      "rerank": {
        "applied": false,
        "rubric": null,
        "new_score": 0.9152696842502716,
        "bonus_applied": false,
        "cap_applied": false,
        "cap_limit": 0.0
      }
    },
    {
      "tier": "ultra_short",
      "score": 0.9130333222377958,
      "ts": "2025-09-14T14:05:50.565Z",
      "scope_id": null,
      "text": "[SGM: 근거 부족 – 답변 보류]\n(필요한 1차 근거 후보: .rules, status/checkpoints/CKPT_72H_RUN.jsonl, app/api.py, docs/0_0_금강 발원문 원본.md)",
      "path": "status/evidence/memory/tiers/ultra_short/20250914/thread_76j4jda7_mfg6h109.jsonl",
      "line_from": 16,
      "line_to": 16,
      "reasons": {
        "kw": 0.2857142857142857,
        "recency": 0.7121983942058503,
        "refs": 0.0,
        "tier_weight": 1.0
      },
      "rerank": {
        "applied": false,
        "rubric": null,
        "new_score": 0.9130333222377958,
        "bonus_applied": false,
        "cap_applied": false,
        "cap_limit": 0.0
      }
    },
    {
      "tier": "ultra_short",
      "score": 0.8885585518346164,
      "ts": "2025-09-16T17:16:13.101Z",
      "scope_id": null,
      "text": "/home/duksan/바탕화면/gumgang_meeting/AGENTS_expand.md",
      "path": "status/evidence/memory/tiers/ultra_short/20250916/thread_pan3h7k9_mfm9ohq0.jsonl",
      "line_from": 2,
      "line_to": 2,
      "reasons": {
        "kw": 0.14285714285714285,
        "recency": 0.9095023482957892,
        "refs": 0.0,
        "tier_weight": 1.0
      },
      "rerank": {
        "applied": false,
        "rubric": null,
        "new_score": 0.8885585518346164,
        "bonus_applied": false,
        "cap_applied": false,
        "cap_limit": 0.0
      }
    },
    {
      "tier": "ultra_short",
      "score": 0.8172609821968111,
      "ts": "2025-09-11T17:57:25.686Z",
      "scope_id": null,
      "text": "[SGM: 근거 부족 – 답변 보류]\n(필요한 1차 근거 후보: .rules, status/checkpoints/CKPT_72H_RUN.jsonl, app/api.py, docs/0_0_금강 발원문 원본.md)",
      "path": "status/evidence/memory/tiers/ultra_short/20250911/688b8836-e404-832d-a65e-6edcbf94a572.jsonl",
      "line_from": 5,
      "line_to": 5,
      "reasons": {
        "kw": 0.2857142857142857,
        "recency": 0.5525778274708756,
        "refs": 0.0,
        "tier_weight": 1.0
      },
      "rerank": {
        "applied": false,
        "rubric": null,
        "new_score": 0.8172609821968111,
        "bonus_applied": false,
        "cap_applied": false,
        "cap_limit": 0.0
      }
    },
    {
      "tier": "ultra_short",
      "score": 0.8162328204449611,
      "ts": "2025-09-11T17:00:40.946Z",
      "scope_id": null,
      "text": "[SGM: 근거 부족 – 답변 보류]\n(필요한 1차 근거 후보: .rules, status/checkpoints/CKPT_72H_RUN.jsonl, app/api.py, docs/0_0_금강 발원문 원본.md)",
      "path": "status/evidence/memory/tiers/ultra_short/20250911/thread_ova3z1dd_mffmki10.jsonl",
      "line_from": 8,
      "line_to": 8,
      "reasons": {
        "kw": 0.2857142857142857,
        "recency": 0.5508642245511257,
        "refs": 0.0,
        "tier_weight": 1.0
      },
      "rerank": {
        "applied": false,
        "rubric": null,
        "new_score": 0.8162328204449611,
        "bonus_applied": false,
        "cap_applied": false,
        "cap_limit": 0.0
      }
    },
    {
      "tier": "ultra_short",
      "score": 0.8161076574332673,
      "ts": "2025-09-11T16:53:45.024Z",
      "scope_id": null,
      "text": "[SGM: 근거 부족 – 답변 보류]\n(필요한 1차 근거 후보: .rules, status/checkpoints/CKPT_72H_RUN.jsonl, app/api.py, docs/0_0_금강 발원문 원본.md)",
      "path": "status/evidence/memory/tiers/ultra_short/20250911/gg_mig_20250911_06ckhx.jsonl",
      "line_from": 9,
      "line_to": 9,
      "reasons": {
        "kw": 0.2857142857142857,
        "recency": 0.5506556195316362,
        "refs": 0.0,
        "tier_weight": 1.0
      },
      "rerank": {
        "applied": false,
        "rubric": null,
        "new_score": 0.8161076574332673,
        "bonus_applied": false,
        "cap_applied": false,
        "cap_limit": 0.0
      }
    },
    {
      "tier": "ultra_short",
      "score": 0.8160703744071813,
      "ts": "2025-09-11T16:51:41.070Z",
      "scope_id": null,
      "text": "[SGM: 근거 부족 – 답변 보류]\n(필요한 1차 근거 후보: .rules, status/checkpoints/CKPT_72H_RUN.jsonl, app/api.py, docs/0_0_금강 발원문 원본.md)",
      "path": "status/evidence/memory/tiers/ultra_short/20250911/6846ebc3-fc3c-8003-972b-7f150ddfc903.jsonl",
      "line_from": 4,
      "line_to": 4,
      "reasons": {
        "kw": 0.2857142857142857,
        "recency": 0.550593481154826,
        "refs": 0.0,
        "tier_weight": 1.0
      },
      "rerank": {
        "applied": false,
        "rubric": null,
        "new_score": 0.8160703744071813,
        "bonus_applied": false,
        "cap_applied": false,
        "cap_limit": 0.0
      }
    },
    {
      "tier": "ultra_short",
      "score": 0.8160413608652926,
      "ts": "2025-09-11T16:50:04.590Z",
      "scope_id": null,
      "text": "[SGM: 근거 부족 – 답변 보류]\n(필요한 1차 근거 후보: .rules, status/checkpoints/CKPT_72H_RUN.jsonl, app/api.py, docs/0_0_금강 발원문 원본.md)",
      "path": "status/evidence/memory/tiers/ultra_short/20250911/68483071-55c8-8003-b33d-bcbd93e0c434.jsonl",
      "line_from": 4,
      "line_to": 4,
      "reasons": {
        "kw": 0.2857142857142857,
        "recency": 0.5505451252516783,
        "refs": 0.0,
        "tier_weight": 1.0
      },
      "rerank": {
        "applied": false,
        "rubric": null,
        "new_score": 0.8160413608652926,
        "bonus_applied": false,
        "cap_applied": false,
        "cap_limit": 0.0
      }
    },
    {
      "tier": "ultra_short",
      "score": 0.8160072933003417,
      "ts": "2025-09-11T16:48:11.282Z",
      "scope_id": null,
      "text": "[SGM: 근거 부족 – 답변 보류]\n(필요한 1차 근거 후보: .rules, status/checkpoints/CKPT_72H_RUN.jsonl, app/api.py, docs/0_0_금강 발원문 원본.md)",
      "path": "status/evidence/memory/tiers/ultra_short/20250911/68483692-2588-8003-acd8-8b219f28d744.jsonl",
      "line_from": 4,
      "line_to": 4,
      "reasons": {
        "kw": 0.2857142857142857,
        "recency": 0.5504883459767601,
        "refs": 0.0,
        "tier_weight": 1.0
      },
      "rerank": {
        "applied": false,
        "rubric": null,
        "new_score": 0.8160072933003417,
        "bonus_applied": false,
        "cap_applied": false,
        "cap_limit": 0.0
      }
    },
    {
      "tier": "ultra_short",
      "score": 0.8159379727102676,
      "ts": "2025-09-11T16:44:20.651Z",
      "scope_id": null,
      "text": "[SGM: 근거 부족 – 답변 보류]\n(필요한 1차 근거 후보: .rules, status/checkpoints/CKPT_72H_RUN.jsonl, app/api.py, docs/0_0_금강 발원문 원본.md)",
      "path": "status/evidence/memory/tiers/ultra_short/20250911/68785bd6-915c-8003-86a8-a5805edd3024.jsonl",
      "line_from": 2,
      "line_to": 2,
      "reasons": {
        "kw": 0.2857142857142857,
        "recency": 0.5503728116599698,
        "refs": 0.0,
        "tier_weight": 1.0
      },
      "rerank": {
        "applied": false,
        "rubric": null,
        "new_score": 0.8159379727102676,
        "bonus_applied": false,
        "cap_applied": false,
        "cap_limit": 0.0
      }
    },
    {
      "tier": "ultra_short",
      "score": 0.8154894962583719,
      "ts": "2025-09-11T16:19:26.218Z",
      "scope_id": null,
      "text": "[SGM: 근거 부족 – 답변 보류]\n(필요한 1차 근거 후보: .rules, status/checkpoints/CKPT_72H_RUN.jsonl, app/api.py, docs/0_0_금강 발원문 원본.md)",
      "path": "status/evidence/memory/tiers/ultra_short/20250911/6845871c-def4-8003-a227-7fcf6c137cad.jsonl",
      "line_from": 10,
      "line_to": 10,
      "reasons": {
        "kw": 0.2857142857142857,
        "recency": 0.5496253509068104,
        "refs": 0.0,
        "tier_weight": 1.0
      },
      "rerank": {
        "applied": false,
        "rubric": null,
        "new_score": 0.8154894962583719,
        "bonus_applied": false,
        "cap_applied": false,
        "cap_limit": 0.0
      }
    },
    {
      "tier": "ultra_short",
      "score": 0.8131018750959553,
      "ts": "2025-09-11T14:05:41.159Z",
      "scope_id": null,
      "text": "[SGM: 근거 부족 – 답변 보류]\n(필요한 1차 근거 후보: .rules, status/checkpoints/CKPT_72H_RUN.jsonl, app/api.py, docs/0_0_금강 발원문 원본.md)",
      "path": "status/evidence/memory/tiers/ultra_short/20250911/thread_dz4jv7iz_mffe0g73.jsonl",
      "line_from": 13,
      "line_to": 13,
      "reasons": {
        "kw": 0.2857142857142857,
        "recency": 0.5456459823027829,
        "refs": 0.0,
        "tier_weight": 1.0
      },
      "rerank": {
        "applied": false,
        "rubric": null,
        "new_score": 0.8131018750959553,
        "bonus_applied": false,
        "cap_applied": false,
        "cap_limit": 0.0
      }
    },
    {
      "tier": "ultra_short",
      "score": 0.8129862273610948,
      "ts": "2025-09-11T13:59:09.481Z",
      "scope_id": null,
      "text": "[SGM: 근거 부족 – 답변 보류]\n(필요한 1차 근거 후보: .rules, status/checkpoints/CKPT_72H_RUN.jsonl, app/api.py, docs/0_0_금강 발원문 원본.md)",
      "path": "status/evidence/memory/tiers/ultra_short/20250911/gg_mig_20250911_06ckhy.jsonl",
      "line_from": 2,
      "line_to": 2,
      "reasons": {
        "kw": 0.2857142857142857,
        "recency": 0.5454532360780153,
        "refs": 0.0,
        "tier_weight": 1.0
      },
      "rerank": {
        "applied": false,
        "rubric": null,
        "new_score": 0.8129862273610948,
        "bonus_applied": false,
        "cap_applied": false,
        "cap_limit": 0.0
      }
    },
    {
      "tier": "ultra_short",
      "score": 0.8123883489711796,
      "ts": "2025-09-11T13:25:20.152Z",
      "scope_id": null,
      "text": "[SGM: 근거 부족 – 답변 보류]\n(필요한 1차 근거 후보: .rules, status/checkpoints/CKPT_72H_RUN.jsonl, app/api.py, docs/0_0_금강 발원문 원본.md)",
      "path": "status/evidence/memory/tiers/ultra_short/20250911/thread_d70obb80_mfffdsmz.jsonl",
      "line_from": 8,
      "line_to": 8,
      "reasons": {
        "kw": 0.2857142857142857,
        "recency": 0.5444567720948233,
        "refs": 0.0,
        "tier_weight": 1.0
      },
      "rerank": {
        "applied": false,
        "rubric": null,
        "new_score": 0.8123883489711796,
        "bonus_applied": false,
        "cap_applied": false,
        "cap_limit": 0.0
      }
    }
  ],
  "ts": "2025-09-17T09:59:12.182Z"
}